MANIFEST.in
README.md
setup.py
ci/__init__.py
ci/test_Boat.py
ci/test_Environment.py
ci/test_utils.py
sailboat_playground/__init__.c
sailboat_playground/__init__.py
sailboat_playground/constants.c
sailboat_playground/constants.py
sailboat_playground.egg-info/PKG-INFO
sailboat_playground.egg-info/SOURCES.txt
sailboat_playground.egg-info/dependency_links.txt
sailboat_playground.egg-info/requires.txt
sailboat_playground.egg-info/top_level.txt
sailboat_playground/engine/Boat.c
sailboat_playground/engine/Boat.py
sailboat_playground/engine/Environment.c
sailboat_playground/engine/Environment.py
sailboat_playground/engine/Manager.c
sailboat_playground/engine/Manager.py
sailboat_playground/engine/__init__.c
sailboat_playground/engine/__init__.py
sailboat_playground/engine/utils.c
sailboat_playground/engine/utils.py
sailboat_playground/visualization/Sailboat.c
sailboat_playground/visualization/Sailboat.py
sailboat_playground/visualization/Viewer.c
sailboat_playground/visualization/Viewer.py
sailboat_playground/visualization/__init__.c
sailboat_playground/visualization/__init__.py
sailboat_playground/visualization/utils.c
sailboat_playground/visualization/utils.py
sailboat_playground/visualization/resources/__init__.c
sailboat_playground/visualization/resources/__init__.py
sailboat_playground/visualization/resources/arrow.png
sailboat_playground/visualization/resources/buoy.png
sailboat_playground/visualization/resources/foil.png
sailboat_playground/visualization/resources/foil_rudder.png
sailboat_playground/visualization/resources/resources.c
sailboat_playground/visualization/resources/resources.py
sailboat_playground/visualization/resources/sailboat.png
sailboat_playground/visualization/resources/speed.png