Metadata-Version: 2.1
Name: sailboat-playground
Version: 0.1.1
Summary: A very simple framework for sailboat simulation and autonomous navigation algorithms development
Home-page: https://github.com/gabriel-milan/sailboat-playground
Author: Gabriel Gazola Milan
Author-email: gabriel.gazola@poli.ufrj.br
License: GPL-3.0
Keywords: framework,python,sailboat,simulation,autonomous navigation
Platform: UNKNOWN
Classifier: Development Status :: 4 - Beta
Classifier: Intended Audience :: Developers
Classifier: Topic :: Software Development :: Libraries :: Python Modules
Classifier: License :: OSI Approved :: GNU General Public License v3 (GPLv3)
Classifier: Programming Language :: Python :: 3
Classifier: Programming Language :: Python :: 3.7
Classifier: Programming Language :: Python :: 3.8
Classifier: Programming Language :: Python :: 3.9
